Metadata-Version: 2.1
Name: ovk-grapher
Version: 0.1
Summary: Graphing package
Author-email: otis.vank@gmail.com
